opensesame_plugins/.DS_Store
opensesame_plugins/eyelink/.DS_Store
opensesame_plugins/eyelink/README.md
opensesame_plugins/eyelink/__init__.py
opensesame_plugins/eyelink/el_camera_setup/.DS_Store
opensesame_plugins/eyelink/el_camera_setup/__init__.py
opensesame_plugins/eyelink/el_camera_setup/el_camera_setup.md
opensesame_plugins/eyelink/el_camera_setup/el_camera_setup.png
opensesame_plugins/eyelink/el_camera_setup/el_camera_setup.py
opensesame_plugins/eyelink/el_camera_setup/el_camera_setup_large.png
opensesame_plugins/eyelink/el_connect/.DS_Store
opensesame_plugins/eyelink/el_connect/__init__.py
opensesame_plugins/eyelink/el_connect/el_connect.md
opensesame_plugins/eyelink/el_connect/el_connect.png
opensesame_plugins/eyelink/el_connect/el_connect.py
opensesame_plugins/eyelink/el_connect/el_connect_large.png
opensesame_plugins/eyelink/el_disconnect/.DS_Store
opensesame_plugins/eyelink/el_disconnect/__init__.py
opensesame_plugins/eyelink/el_disconnect/el_disconnect.md
opensesame_plugins/eyelink/el_disconnect/el_disconnect.png
opensesame_plugins/eyelink/el_disconnect/el_disconnect.py
opensesame_plugins/eyelink/el_disconnect/el_disconnect_large.png
opensesame_plugins/eyelink/el_drift_check/.DS_Store
opensesame_plugins/eyelink/el_drift_check/__init__.py
opensesame_plugins/eyelink/el_drift_check/el_drift_check.md
opensesame_plugins/eyelink/el_drift_check/el_drift_check.png
opensesame_plugins/eyelink/el_drift_check/el_drift_check.py
opensesame_plugins/eyelink/el_drift_check/el_drift_check_large.png
opensesame_plugins/eyelink/el_gaze_trigger/.DS_Store
opensesame_plugins/eyelink/el_gaze_trigger/__init__.py
opensesame_plugins/eyelink/el_gaze_trigger/el_gaze_trigger.md
opensesame_plugins/eyelink/el_gaze_trigger/el_gaze_trigger.png
opensesame_plugins/eyelink/el_gaze_trigger/el_gaze_trigger.py
opensesame_plugins/eyelink/el_gaze_trigger/el_gaze_trigger_large.png
opensesame_plugins/eyelink/el_send_command/.DS_Store
opensesame_plugins/eyelink/el_send_command/__init__.py
opensesame_plugin_eyelink-2.1.1197.0.dist-info/LICENSE
opensesame_plugin_eyelink-2.1.1197.0.dist-info/METADATA
opensesame_plugin_eyelink-2.1.1197.0.dist-info/WHEEL
opensesame_plugin_eyelink-2.1.1197.0.dist-info/RECORD
