Metadata-Version: 2.1
Name: opensesame-plugin-eyelink
Version: 2.1.1197.0
Summary: Extension package for OpenSesame which adds support for EyeLink devices by SR Research.
License: GPL-3.0-only
Author: Jono Batten
Author-email: jono@sr-research.com
Requires-Python: >=3.9
Classifier: License :: OSI Approved :: GNU General Public License v3 (GPLv3)
Classifier: Programming Language :: Python :: 3
Classifier: Programming Language :: Python :: 3.9
Classifier: Programming Language :: Python :: 3.10
Classifier: Programming Language :: Python :: 3.11
Classifier: Programming Language :: Python :: 3.12
Requires-Dist: opensesame-core (>=4.0.0a0)
Requires-Dist: opensesame-eyelink-coregraphics (>=2.1.1197)
Requires-Dist: sr-research-pylink (>=2.1.0)
